MANIFEST.in
README.rst
setup.py
bin/joke-scripts
docs/dummy_file1.txt
docs/dummy_file2.txt
funniesting/__init__.py
funniesting/command_line.py
funniesting/text.py
funniesting.egg-info/PKG-INFO
funniesting.egg-info/SOURCES.txt
funniesting.egg-info/dependency_links.txt
funniesting.egg-info/entry_points.txt
funniesting.egg-info/not-zip-safe
funniesting.egg-info/requires.txt
funniesting.egg-info/top_level.txt
funniesting/data/data.json